{
  "project_info": {
    "project_number": "884686730182",
    "project_id": "todoapp-6e2f7",
    "storage_bucket": "todoapp-6e2f7.appspot.com"
  },
  "client": [
    {
      "client_info": {
        "mobilesdk_app_id": "1:884686730182:android:0972781c8175fef866f8c7",
        "android_client_info": {
          "package_name": "com.example.todo_app"
        }
      },
      "oauth_client": [
        {
          "client_id": "884686730182-rphv8eu8n7o2qs58gh2apa9ca3l2qofl.apps.googleusercontent.com",
          "client_type": 3
        }
      ],
      "api_key": [
        {
          "current_key": "AIzaSyCv1lEJOvNsjNVi9SrIFn3AOG3VLsnuh40"
        }
      ],
      "services": {
        "appinvite_service": {
          "other_platform_oauth_client": [
            {
              "client_id": "884686730182-rphv8eu8n7o2qs58gh2apa9ca3l2qofl.apps.googleusercontent.com",
              "client_type": 3
            }
          ]
        }
      }
    }
  ],
  "configuration_version": "1"
}